shasha/__init__.py
shasha/decision_tree.py
shasha/knn.py
shasha/linear_regression.py
shasha/logistic_regression.py
shasha/multiple_regression.py
shasha/random_forest.py
tests/__init__.py
tests/test_decision_tree.py
tests/test_knn.py
tests/test_linear_regression.py
tests/test_logistic_regression.py
tests/test_multiple_regression.py
tests/test_random_forest.py
shasha-0.1.0.dist-info/LICENSE
shasha-0.1.0.dist-info/METADATA
shasha-0.1.0.dist-info/WHEEL
shasha-0.1.0.dist-info/top_level.txt
shasha-0.1.0.dist-info/RECORD
